pkrbot.cp311-win32.pyd
pkrbot-1.1.0.dist-info/LICENSE
pkrbot-1.1.0.dist-info/METADATA
pkrbot-1.1.0.dist-info/WHEEL
pkrbot-1.1.0.dist-info/top_level.txt
pkrbot-1.1.0.dist-info/RECORD
