Metadata-Version: 2.1
Name: pkrbot
Version: 1.1.0
Summary: Fast poker hand evaluation library with eval7-compatible API
Author: Bobby Costin
License: MIT
Project-URL: Homepage, https://github.com/bossbobster/pkrbot
Keywords: poker,hand evaluation,eval7,cards,game,pokerbots
Classifier: Development Status :: 4 - Beta
Classifier: Intended Audience :: Developers
Classifier: License :: OSI Approved :: MIT License
Classifier: Programming Language :: Python :: 3
Classifier: Programming Language :: Python :: 3.8
Classifier: Programming Language :: Python :: 3.9
Classifier: Programming Language :: Python :: 3.10
Classifier: Programming Language :: Python :: 3.11
Classifier: Programming Language :: Python :: 3.12
Classifier: Programming Language :: Python :: 3.13
Classifier: Programming Language :: Cython
Classifier: Topic :: Games/Entertainment
Requires-Python: >=3.8
License-File: LICENSE
